Workbook

Sheet Summary
A1: UK Train Rides – Week 2 Final Question List | الشكل النهائي للأسبوع 2
A3: Tier | B3: Questions | C3: Done | D3: % Done
A4: Tier 1 | B4: =COUNTIF(Questions!$B:$B,A4) -> 11 | C4: =COUNTIFS(Questions!$B:$B,A4,Questions!$J:$J,"Done") -> 11 | D4: =IF(B4=0,0,C4/B4) -> 1
A5: Tier 2 | B5: =COUNTIF(Questions!$B:$B,A5) -> 21 | C5: =COUNTIFS(Questions!$B:$B,A5,Questions!$J:$J,"Done") -> 21 | D5: =IF(B5=0,0,C5/B5) -> 1
A6: Tier 3 | B6: =COUNTIF(Questions!$B:$B,A6) -> 14 | C6: =COUNTIFS(Questions!$B:$B,A6,Questions!$J:$J,"Done") -> 14 | D6: =IF(B6=0,0,C6/B6) -> 1
A7: KPI | B7: =COUNTIF(Questions!$B:$B,A7) -> 21 | C7: =COUNTIFS(Questions!$B:$B,A7,Questions!$J:$J,"Done") -> 21 | D7: =IF(B7=0,0,C7/B7) -> 1
A8: Total | B8: =SUM(B4:B7) -> 67 | C8: =SUM(C4:C7) -> 67 | D8: =IF(B8=0,0,C8/B8) -> 1
A10: Axis | B10: Questions
A11: Revenue | B11: =COUNTIF(Questions!$C:$C,A11) -> 9
A12: Tickets | B12: =COUNTIF(Questions!$C:$C,A12) -> 9
A13: Routes | B13: =COUNTIF(Questions!$C:$C,A13) -> 12
A14: Performance | B14: =COUNTIF(Questions!$C:$C,A14) -> 9
A15: Refunds | B15: =COUNTIF(Questions!$C:$C,A15) -> 9
A16: Customers | B16: =COUNTIF(Questions!$C:$C,A16) -> 7
A17: Cross-axis | B17: =COUNTIF(Questions!$C:$C,A17) -> 6
A18: Forecast | B18: =COUNTIF(Questions!$C:$C,A18) -> 6
A19: Total | B19: =SUM(B11:B18) -> 67
A21: Notes: only questions answered in Final_Project.ipynb are listed. Cell numbers (#) refer to 0-based code cell index in the notebook. Counts update automatically.

Sheet Questions
A1: ID | B1: Tier | C1: Axis | D1: المحور | E1: السؤال | F1: Question | G1: Columns used | H1: Tool | I1: Note | J1: Status | K1: Notebook cell(s) | L1: Python code (from Final_Project.ipynb) | M1: Result (notebook output)
A2: D21 | B2: Tier 1 | C2: Refunds | D2: الاسترداد | E2: إيه التكلفة الإجمالية للتأخيرات والإلغاءات (الإيراد المعرّض للخسارة) كنسبة من الإيراد، وأنهي سبب بيكلّفنا أكتر؟ | F2: What is the total cost of delays and cancellations (revenue at risk) as a share of revenue, and which cause costs the most? | G2: Price, Journey Status, Refund Request, Reason for Delay | H2: SQL | I2: Original | J2: Done | K2: #58 | L2: loss = df[df.cancelled | df.refund] print("Revenue at risk:", loss.Price.sum(), f"= {loss.Price.sum() / df.Price.sum():.1%} of revenue") print("\nBy cause:\n", loss.groupby("Reason for Delay").Price.agg(tickets="size", revenue_at_risk="sum").sort_values("revenue_at_risk", ascending=False)) print("\nBy status:\n", loss.groupby("Journey Status").Price.sum()) | M2: Revenue at risk: 71621 = 9.7% of revenue By cause: tickets revenue_at_risk Reason for Delay Technical Issue 551 18185 Staffing 348 13881 Signal Failure 579 13787 Traffic 274 8420 Weather 237 7168 Staff Shortage 229 6092 Weather Conditions 208 4088 By status: Journey Status Cancelled 45456 Delayed 26165 Name: Price, dtype: int64
A3: D18 | B3: Tier 1 | C3: Refunds | D3: الاسترداد | E3: هل كل رحلة ملغية عليها طلب استرداد؟ وإيه نسبة الملغية اللي مفيش عليها طلب؟ | F3: Does every cancelled journey have a refund request? What share of cancellations have none? | G3: Journey Status, Refund Request | H3: SQL | I3: Original | J3: Done | K3: #39 | L3: c = df[df["cancelled"]] print(f"Cancelled: {len(c)} | with refund request: {c['refund'].sum()} ({c['refund'].mean():.1%}) | without: {(~c['refund']).sum()} ({(~c['refund']).mean():.1%})") print("Revenue of cancelled journeys with no refund request:", c[~c["refund"]]["Price"].sum()) | M3: Cancelled: 1880 | with refund request: 572 (30.4%) | without: 1308 (69.6%) Revenue of cancelled journeys with no refund request: 32919
A4: X3 | B4: Tier 1 | C4: Cross-axis | D4: متقاطع | E4: أنهي خطوط عالية الإيراد لكن أداؤها ضعيف (تأخير أو إلغاء عالي)؟ | F4: Which routes have high revenue but poor punctuality (high delay or cancellation rate)? | G4: Departure Station, Arrival Destination, Price, Journey Status | H4: SQL + Python | I4: Original | J4: Done | K4: #40, #86 | L4: r = df.groupby("route").agg(tickets=("Price", "size"), revenue=("Price", "sum"), disruption_rate=("disrupted", "mean")) top = r.sort_values("revenue", ascending=False).head(15).copy() top["disruption_rate"] = (top.disruption_rate * 100).round(1) avg = df.disrupted.mean() * 100 top["above_network_avg"] = top.disruption_rate > avg print(f"Network disruption rate: {avg:.1f}%") print(top) | M4: Network disruption rate: 13.2% tickets revenue \ route London Kings Cross -> York 3922 183193 Liverpool Lime Street -> London Euston 1097 113299 London Paddington -> Reading 3873 65368 London Euston -> Manchester Piccadilly 712 61004 London St Pancras -> Birmingham New Street 3471 52869 London Euston -> Birmingham New Street 4209 50349 Manchester Piccadilly -> London Euston 345 33860 Birmingham New Street -> London St Pancras 702 19011 Manchester Piccadilly -> Liverpool Lime Street 4628 17310 Manchester Piccadilly -> London Paddington 144 16432 London Paddington -> Oxford 485 12859 Liverpool Lime Street -> Manchester Piccadilly 3002 11950 York -> Peterborough 242 10764 London Kings Cross -> Liverpool Lime Street 144 10373 London St Pancras -> Leicester 337 7354 disruption_rate \ route London Kings Cross -> York 8.4 Liverpool Lime Street -> London Euston 80.1 London Paddington -> Reading 9.1 London Euston -> Manchester Piccadilly 6.3 London St Pancras -> Birmingham New Street 7.9 London Euston -> Birmingham New Street 10.8 Manchester Piccadilly -> London Euston 70.4 Birmingham New Street -> London St Pancras 7.3 Manchester Piccadilly -> Liverpool Lime Street 13.9 Manchester Piccadilly -> London Paddington 5.6 London Paddington -> Oxford 13.0 Liverpool Lime Street -> Manchester Piccadilly 7.7 York -> Peterborough 9.1 London Kings Cross -> Liverpool Lime Street 0.7 London St Pancras -> Leicester 4.7 above_network_avg route London Kings Cross -> York False Liverpool Lime Street -> London Euston True London Paddington -> Reading False London Euston -> Manchester Piccadilly False London St Pancras -> Birmingham New Street False London Euston -> Birmingham New Street False Manchester Piccadilly -> London Euston True Birmingham New Street -> London St Pancras False Manchester Piccadilly -> Liverpool Lime Street True Manchester Piccadilly -> London Paddington False London Paddington -> Oxford False Liverpool Lime Street -> Manchester Piccadilly False York -> Peterborough False London Kings Cross -> Liverpool Lime Street False London St Pancras -> Leicester False
A5: D3 | B5: Tier 1 | C5: Revenue | D5: الإيرادات | E5: إيه نسبة الإيراد اللي بتيجي من أعلى 20% من الخطوط؟ (Pareto) | F5: What share of revenue comes from the top 20% of routes? (Pareto) | G5: Departure Station, Arrival Destination, Price | H5: Python | I5: Original | J5: Done | K5: #36, #63 | L5: rev = df.groupby("route").Price.sum().sort_values(ascending=False).reset_index() rev["cum_share"] = rev.Price.cumsum() / rev.Price.sum() top20 = int(len(rev) * 0.2) print(f"Routes: {len(rev)} | top 20% = {top20} routes -> {rev.loc[:top20 - 1, 'Price'].sum() / rev.Price.sum():.1%} of revenue") print("Routes needed for 80% of revenue:", (rev.cum_share < 0.8).sum() + 1) fig, ax = plt.subplots(figsize=(10, 4)); ax.bar(range(len(rev)), rev.Price, color="#4C78A8"); ax.set_ylabel("Revenue") ax2 = ax.twinx(); ax2.plot(range(len(rev)), rev.cum_share * 100, color="#E45756"); ax2.axhline(80, ls="--", color="gray"); ax2.set_ylabel("Cumulative %") ax.set_title("Pareto: revenue by route"); plt.show() | M5: Routes: 65 | top 20% = 13 routes -> 87.4% of revenue Routes needed for 80% of revenue: 9 [chart - see notebook]
A6: D1 | B6: Tier 1 | C6: Revenue | D6: الإيرادات | E6: هل نمو الإيراد الشهري سببه زيادة عدد التذاكر ولا ارتفاع متوسط السعر؟ | F6: Is monthly revenue growth driven by ticket volume or by higher average price? | G6: Date of Journey, Price | H6: SQL | I6: Original | J6: Done | K6: #35, #48 | L6: m = df.groupby("month").agg(tickets=("Price", "size"), revenue=("Price", "sum")) m["avg_price"] = m.revenue / m.tickets m["revenue_change"] = m.revenue.diff() m["volume_effect"] = m.tickets.diff() * m.avg_price.shift() # (t1-t0) * p0 m["price_effect"] = m.avg_price.diff() * m.tickets # (p1-p0) * t1 print(m.round(1)) print("\nvolume_effect + price_effect = revenue_change (exact decomposition)") | M6: tickets revenue avg_price revenue_change volume_effect \ month 2024-01 8111 199618 24.6 NaN NaN 2024-02 7644 159374 20.8 -40244.0 -11493.2 2024-03 8117 195147 24.0 35773.0 9861.8 2024-04 7781 187782 24.1 -7365.0 -8078.0 price_effect month 2024-01 NaN 2024-02 -28750.8 2024-03 25911.2 2024-04 713.0 volume_effect + price_effect = revenue_change (exact decomposition)
A7: F1 | B7: Tier 1 | C7: Forecast | D7: توقع | E7: كام عدد الرحلات المتوقع في مايو 2024، وإيه هامش الخطأ؟ | F7: How many journeys are expected in May 2024, and what is the error margin? | G7: Date of Journey | H7: Python (scikit-learn) | I7: Original | J7: Done | K7: #42 | L7: from sklearn.linear_model import Ridge from sklearn.metrics import mean_absolute_error MAY = pd.date_range("2024-05-01", "2024-05-31") def design(idx, t0): X = pd.get_dummies(pd.Series(pd.Categorical(idx.dayofweek, categories=range(7)), index=idx)).astype(int) X.columns = [f"dow{c}" for c in X.columns] # عمود لكل يوم أسبوع X["t"] = (idx - t0).days # الاتجاه العام return X def fit_forecast(series, horizon=MAY, holdout=28): t0 = series.index[0]; X = design(series.index, t0) m = Ridge(alpha=1.0).fit(X.iloc[:-holdout], series.iloc[:-holdout]) mae = mean_absolute_error(series.iloc[-holdout:], m.predict(X.iloc[-holdout:])) naive = mean_absolute_error(series.iloc[-holdout:], series.shift(7).iloc[-holdout:]) m = Ridge(alpha=1.0).fit(X, series) resid = (series - m.predict(X)).std() fc = pd.Series(m.predict(design(horizon, t0)), index=horizon).clip(lower=0) return fc, mae, naive, resid daily = df.groupby("jd").size().reindex(pd.date_range(df["jd"].min(), df["jd"].max()), fill_value=0) fc, mae, naive, sd = fit_forecast(daily) print(f"Forecast journeys May 2024: {fc.sum():,.0f} (95% interval about +/- {1.96 * sd * np.sqrt(len(fc)):,.0f})") print(f"Holdout MAE: model {mae:.1f} vs same-day-last-week {naive:.1f} tickets/day") | M7: Forecast journeys May 2024: 8,304 (95% interval about +/- 423) Holdout MAE: model 21.9 vs same-day-last-week 32.4 tickets/day
A8: F2 | B8: Tier 1 | C8: Forecast | D8: توقع | E8: إيه الإيراد المتوقع لكل يوم في مايو، ومتى أيام الذروة؟ | F8: What is the forecasted revenue per day in May, and when are the peak days? | G8: Date of Journey, Price | H8: Python (scikit-learn) | I8: Original | J8: Done | K8: #43 | L8: rev_daily = df.groupby("jd")["Price"].sum().reindex(pd.date_range(df["jd"].min(), df["jd"].max()), fill_value=0) fcr, mae_r, naive_r, _ = fit_forecast(rev_daily) print(f"Forecast revenue May 2024: {fcr.sum():,.0f} | holdout MAE model {mae_r:.0f} vs naive {naive_r:.0f}") print(fcr.sort_values(ascending=False).head(5).round(0)) rev_daily.plot(figsize=(10, 3), label="actual"); fcr.plot(label="forecast May", color="red") plt.legend(); plt.title("Daily revenue: actual + May forecast"); plt.show() fcr.round(0).to_csv("forecast_may_daily_revenue.csv", header=["forecast_revenue"]) | M8: Forecast revenue May 2024: 195,893 | holdout MAE model 880 vs naive 991 2024-05-29 6862.0 2024-05-22 6846.0 2024-05-15 6831.0 2024-05-08 6816.0 2024-05-01 6800.0 dtype: float64 [chart - see notebook]
A9: F3 | B9: Tier 1 | C9: Forecast | D9: توقع | E9: إيه الطلب المتوقع على كل درجة ونوع تذكرة (Standard/First × Advance/Off-Peak/Anytime)؟ | F9: What is the expected demand per ticket class and ticket type? | G9: Ticket Class, Ticket Type, Date of Journey | H9: Python (scikit-learn) | I9: Original | J9: Done | K9: #44 | L9: rows = [] full = pd.date_range(df["jd"].min(), df["jd"].max()) for cls, typ in product(df["Ticket Class"].unique(), df["Ticket Type"].unique()): s = df[(df["Ticket Class"] == cls) & (df["Ticket Type"] == typ)].groupby("jd").size().reindex(full, fill_value=0) f, *_ = fit_forecast(s) rows.append({"class": cls, "ticket_type": typ, "Jan-Apr/day": round(s.mean(), 1), "May total": round(f.sum()), "May/day": round(f.mean(), 1)}) print(pd.DataFrame(rows).sort_values("May total", ascending=False).to_string(index=False)) | M9: class ticket_type Jan-Apr/day May total May/day Standard Advance 130.6 3921 126.5 Standard Off-Peak 65.7 2204 71.1 Standard Anytime 40.1 1353 43.6 First Class Advance 14.6 426 13.8 First Class Off-Peak 6.6 244 7.9 First Class Anytime 4.0 155 5.0
A10: D14 | B10: Tier 1 | C10: Performance | D10: الأداء | E10: لكل سبب تأخير، إيه متوسط مدة التأخير بالدقائق؟ (أكتر سبب تكراراً مش بالضرورة الأطول) | F10: For each delay reason, what is the average delay in minutes? (The most frequent cause is not necessarily the longest) | G10: Reason for Delay, Arrival Time, Actual Arrival Time | H10: SQL + Python | I10: Original | J10: Done | K10: #37, #54 | L10: t = df[df.delayed].groupby("Reason for Delay").delay_min.agg(delays="size", avg_min="mean", median_min="median", max_min="max").round(1) print(t.sort_values("avg_min", ascending=False)) print("\nMost frequent cause:", t.delays.idxmax(), "| longest average:", t.avg_min.idxmax()) | M10: delays avg_min median_min max_min Reason for Delay Staff Shortage 183 74.9 50.0 179.0 Signal Failure 451 51.8 37.0 180.0 Weather 758 46.8 48.0 99.0 Traffic 87 32.3 26.0 89.0 Weather Conditions 169 30.5 29.0 69.0 Staffing 172 25.9 20.5 88.0 Technical Issue 472 24.9 24.0 80.0 Most frequent cause: Weather | longest average: Staff Shortage
A11: D19 | B11: Tier 1 | C11: Refunds | D11: الاسترداد | E11: هل مدة التأخير بتأثر على احتمال طلب الاسترداد؟ من أي حد بيبدأ العملاء يطلبوا؟ | F11: Does delay length affect refund likelihood? At what threshold do customers start requesting? | G11: Arrival Time, Actual Arrival Time, Refund Request | H11: Python | I11: Original | J11: Done | K11: #38 | L11: d = df[df["delayed"]].copy() d["delay_bucket"] = pd.cut(d["delay_min"], [-1, 15, 30, 45, 60, 90, 200]) print(d.groupby("delay_bucket", observed=True).agg(journeys=("refund", "size"), refund_rate=("refund", "mean")).round(3)) print("corr(delay_min, refund):", round(d["delay_min"].corr(d["refund"].astype(int)), 3)) | M11: journeys refund_rate delay_bucket (-1, 15] 450 0.458 (15, 30] 505 0.461 (30, 45] 531 0.181 (45, 60] 483 0.023 (60, 90] 140 0.000 (90, 200] 183 0.000 corr(delay_min, refund): -0.36
A12: D22 | B12: Tier 1 | C12: Customers | D12: العملاء | E12: مدة الحجز المسبق: إزاي بتتوزع، وهل الحجز المبكر أرخص فعلاً؟ | F12: How is booking lead time distributed, and is booking earlier actually cheaper? | G12: Date of Purchase, Date of Journey, Price | H12: SQL + Python | I12: Original | J12: Done | K12: #41, #59 | L12: print("Lead time days:", df.lead_days.describe().round(1).to_dict()) print(df.groupby(pd.cut(df.lead_days, [-1, 0, 1, 3, 7, 14, 30]), observed=True).Price.agg(tickets="size", avg_price="mean").round(1)) print("corr(lead_days, price):", round(df.lead_days.corr(df.Price), 3)) print(df.groupby(["Ticket Type", df.lead_days.eq(0)]).Price.mean().unstack().round(1).rename(columns={False: "booked ahead", True: "same day"})) print("Note: in this data every Advance ticket is booked 1+ days ahead and every Anytime/Off-Peak ticket is bought same day,") print("so the same-day premium is really the ticket-type price difference (lead time and ticket type overlap).") | M12: Lead time days: {'count': 31653.0, 'mean': 1.7, 'std': 3.9, 'min': 0.0, '25%': 0.0, '50%': 1.0, '75%': 1.0, 'max': 28.0} tickets avg_price lead_days (-1, 0] 14092 30.7 (0, 1] 13744 17.6 (1, 3] 651 18.0 (3, 7] 940 17.0 (7, 14] 1256 17.2 (14, 30] 970 18.7 corr(lead_days, price): -0.081 lead_days booked ahead same day Ticket Type Advance 17.6 NaN Anytime NaN 39.2 Off-Peak NaN 25.5 Note: in this data every Advance ticket is booked 1+ days ahead and every Anytime/Off-Peak ticket is bought same day, so the same-day premium is really the ticket-type price difference (lead time and ticket type overlap).
... A68: Q23 | B68: KPI | C68: Customers | D68: العملاء | E68: العملاء بيحجزوا قبل الرحلة بكام يوم في المتوسط، وإزاي ده بيأثر على السعر؟ | F68: How many days before the journey do customers book on average, and how does that affect price? | G68: Date of Purchase, Date of Journey, Price | H68: SQL | I68: Original | J68: Done | K68: #41 | L68: df["lead_days"] = (df["jd"] - pd.to_datetime(df["Date of Purchase"])).dt.days # عدد الأيام بين الشراء والرحلة print(df["lead_days"].describe().round(1)) print(df.groupby(pd.cut(df["lead_days"], [-1, 0, 1, 3, 7, 14, 30]), observed=True)["Price"].agg(tickets="size", avg_price="mean").round(1)) print("corr(lead_days, price):", round(df["lead_days"].corr(df["Price"]), 3)) | M68: count 31653.0 mean 1.7 std 3.9 min 0.0 25% 0.0 50% 1.0 75% 1.0 max 28.0 Name: lead_days, dtype: float64 tickets avg_price lead_days (-1, 0] 14092 30.7 (0, 1] 13744 17.6 (1, 3] 651 18.0 (3, 7] 940 17.0 (7, 14] 1256 17.2 (14, 30] 970 18.7 corr(lead_days, price): -0.081
